docs/source/conf.py
dummy_package/__init__.py
dummy_package/dummy_module1.py
dummy_package/dummy_module2.py
plugin_manager/__init__.py
plugin_manager/main.py
plugin_manager/version.py
plugin_manager/gui/__init__.py
plugin_manager/gui/tk_gui.py
plugin_manager/gui/tk_widgets.py
plugin_manager/model/__init__.py
plugin_manager/model/json_handler.py
plugin_manager/model/plugin.py
tests/plugin_fixtures.py
tests/test_tools.py
tests/model/test_json_handler.py
tests/model/test_plugin.py
json_plugin_mgr-0.1.2.dist-info/AUTHORS.txt
json_plugin_mgr-0.1.2.dist-info/LICENSE.txt
json_plugin_mgr-0.1.2.dist-info/METADATA
json_plugin_mgr-0.1.2.dist-info/WHEEL
json_plugin_mgr-0.1.2.dist-info/entry_points.txt
json_plugin_mgr-0.1.2.dist-info/top_level.txt
json_plugin_mgr-0.1.2.dist-info/RECORD
